almost_requested/__init__.py
almost_requested/ar.py
almost_requested-1.dist-info/METADATA
almost_requested-1.dist-info/WHEEL
almost_requested-1.dist-info/licenses/LICENSE
almost_requested-1.dist-info/RECORD
