Metadata-Version: 2.1
Name: almost_requested
Version: 1
Summary: Make APIs more human
Project-URL: Homepage, https://github.com/dooferlad/almost_requested
Project-URL: Bug Tracker, https://github.com/dooferlad/almost_requested/issues
Author-email: James Tunnicliffe <james@nanosheep.org>
License-File: LICENSE
Classifier: License :: OSI Approved :: MIT License
Classifier: Operating System :: OS Independent
Classifier: Programming Language :: Python :: 3
Requires-Python: >=3.7
Requires-Dist: requests
